{
  "searchConfig": {
    "tripType": "one-way",
    "origin": "Istanbul",
    "destination": "Ankara",
    "departureDate": "24.05.2026",
    "adults": 1,
    "children": 0,
    "nonStop": false
  },
  "scrapedAt": "2026-05-21T18:51:40.055Z",
  "flights": [
    {
      "airline": "Pegasus",
      "departureTime": "19:00",
      "arrivalTime": "20:00",
      "duration": "",
      "price": "1.820,57 TL",
      "isDirect": true
    },
    {
      "airline": "Pegasus",
      "departureTime": "19:00",
      "arrivalTime": "20:00",
      "duration": "",
      "price": "1.945,24 TL",
      "isDirect": true
    },
    {
      "airline": "AJet",
      "departureTime": "01:30",
      "arrivalTime": "02:35",
      "duration": "1s 5dk",
      "price": "2.156,47 TL",
      "isDirect": true
    },
    {
      "airline": "AJet",
      "departureTime": "23:00",
      "arrivalTime": "00:05",
      "duration": "1s 5dk",
      "price": "2.156,47 TL",
      "isDirect": true
    },
    {
      "airline": "Pegasus",
      "departureTime": "00:30",
      "arrivalTime": "01:30",
      "duration": "",
      "price": "2.268,87 TL",
      "isDirect": true
    }
  ]
}